{
	"id": "e448f0d9-67d6-445c-8e60-fd904f750ac2",
	"name": "SwaggerPetstore",
	"values": [
		{
			"key": "host",
			"value": "https://petstore.swagger.io/v2",
			"type": "default",
			"enabled": true
		},
		{
			"key": "userName",
			"value": "",
			"type": "any",
			"enabled": true
		},
		{
			"key": "email",
			"value": "",
			"type": "any",
			"enabled": true
		},
		{
			"key": "phone",
			"value": "",
			"type": "any",
			"enabled": true
		},
		{
			"key": "firstName",
			"value": "",
			"type": "any",
			"enabled": true
		},
		{
			"key": "lastName",
			"value": "",
			"type": "any",
			"enabled": true
		},
		{
			"key": "password",
			"value": "",
			"type": "any",
			"enabled": true
		},
		{
			"key": "id",
			"value": "",
			"type": "any",
			"enabled": true
		},
		{
			"key": "userStatus",
			"value": "",
			"type": "any",
			"enabled": true
		},
		{
			"key": "id1",
			"value": "",
			"type": "any",
			"enabled": true
		},
		{
			"key": "userName1",
			"value": "",
			"type": "any",
			"enabled": true
		},
		{
			"key": "firstName1",
			"value": "",
			"type": "any",
			"enabled": true
		},
		{
			"key": "lastName1",
			"value": "",
			"type": "any",
			"enabled": true
		},
		{
			"key": "email1",
			"value": "",
			"type": "any",
			"enabled": true
		},
		{
			"key": "password1",
			"value": "",
			"type": "any",
			"enabled": true
		},
		{
			"key": "phone1",
			"value": "",
			"type": "any",
			"enabled": true
		},
		{
			"key": "userStatus1",
			"value": "",
			"type": "any",
			"enabled": true
		},
		{
			"key": "category_id",
			"value": "",
			"type": "any",
			"enabled": true
		},
		{
			"key": "category_name",
			"value": "",
			"type": "any",
			"enabled": true
		},
		{
			"key": "pet_name",
			"value": "",
			"type": "any",
			"enabled": true
		},
		{
			"key": "photoUrls",
			"value": "",
			"type": "any",
			"enabled": true
		},
		{
			"key": "tag_id",
			"value": "",
			"type": "any",
			"enabled": true
		},
		{
			"key": "tag_name",
			"value": "",
			"type": "any",
			"enabled": true
		},
		{
			"key": "petId",
			"value": "",
			"type": "any",
			"enabled": true
		},
		{
			"key": "Id",
			"value": "",
			"type": "any",
			"enabled": true
		},
		{
			"key": "order_id",
			"value": "",
			"type": "any",
			"enabled": true
		},
		{
			"key": "quantity",
			"value": "",
			"type": "any",
			"enabled": true
		},
		{
			"key": "shipDate",
			"value": "",
			"type": "any",
			"enabled": true
		},
		{
			"key": "status",
			"value": "",
			"type": "any",
			"enabled": true
		},
		{
			"key": "complete",
			"value": "",
			"type": "any",
			"enabled": true
		}
	],
	"_postman_variable_scope": "environment",
	"_postman_exported_at": "2023-08-05T10:17:59.638Z",
	"_postman_exported_using": "Postman/10.16.5"
}